[{"Time_and_Weather": [[{"time": "00:00", "weather": "´¸"}, {"time": "03:00", "weather": "´¸"}, {"time": "06:00", "weather": "´¸"}, {"time": "09:00", "weather": "´¸"}, {"time": "12:00", "weather": "´¸"}, {"time": "15:00", "weather": "´¸"}, {"time": "18:00", "weather": "´¸"}, {"time": "21:00", "weather": "´¸"}]], "locatin": "¤¤°Ï"}, {"Time_and_Weather": [[{"time": "00:00", "weather": "´¸"}, {"time": "03:00", "weather": "´¸"}, {"time": "06:00", "weather": "´¸"}, {"time": "09:00", "weather": "´¸"}, {"time": "12:00", "weather": "´¸"}, {"time": "15:00", "weather": "´¸"}, {"time": "18:00", "weather": "´¸"}, {"time": "21:00", "weather": "´¸"}]], "locatin": "ªF°Ï"}]